kore_plugins_beaker/__init__.py
kore_plugins_beaker/plugins/__init__.py
kore_plugins_beaker/plugins/base.py
kore_plugins_beaker/plugins/cache.py
kore_plugins_beaker-0.0.1.dist-info/DESCRIPTION.rst
kore_plugins_beaker-0.0.1.dist-info/entry_points.txt
kore_plugins_beaker-0.0.1.dist-info/METADATA
kore_plugins_beaker-0.0.1.dist-info/metadata.json
kore_plugins_beaker-0.0.1.dist-info/RECORD
kore_plugins_beaker-0.0.1.dist-info/top_level.txt
kore_plugins_beaker-0.0.1.dist-info/WHEEL
