Metadata-Version: 2.0
Name: kore-plugins-beaker
Version: 0.0.1
Summary: UNKNOWN
Home-page: https://github.com/kore-plugins/kore-plugins-beaker
Author: Artur Maciąg
Author-email: maciag.artur@gmail.com
License: UNKNOWN
Platform: UNKNOWN
Classifier: Intended Audience :: Developers
Classifier: Programming Language :: Python :: 2.7
Classifier: Programming Language :: Python :: 3.4
Classifier: Programming Language :: Python :: 3.6
Classifier: Topic :: Software Development :: Libraries
Requires-Dist: kore
Requires-Dist: kore-shell (>=0.0.2)
Requires-Dist: beaker
